Multi_Layer_NN/Multi_Layer_NN.py
Multi_Layer_NN/__init__.py
Multi_Layer_NN-0.0.2.dist-info/METADATA
Multi_Layer_NN-0.0.2.dist-info/WHEEL
Multi_Layer_NN-0.0.2.dist-info/top_level.txt
Multi_Layer_NN-0.0.2.dist-info/RECORD
