Metadata-Version: 2.1
Name: Multi-Layer-NN
Version: 0.0.2
Summary: A Multy Layer Neural Network Class
Home-page: UNKNOWN
Author: Andreas Probst
Author-email: andreaspadprobst@gmail.com
License: MIT
Platform: UNKNOWN
Classifier: License :: OSI Approved :: MIT License
Requires-Dist: matplotlib (>=2.2.5)
Requires-Dist: numpy (>=1.16.6)
